manot/__init__.py
manot/logger.py
manot/manot.py
manot/upload_manager.py
manot-0.8.5.dist-info/LICENSE
manot-0.8.5.dist-info/METADATA
manot-0.8.5.dist-info/WHEEL
manot-0.8.5.dist-info/top_level.txt
manot-0.8.5.dist-info/RECORD
