Metadata-Version: 2.1
Name: manot
Version: 0.8.5
Summary: manot AI is a model observability platform to monitor computer vision performance in real-time.
Home-page: https://www.manot.ai
Author: manot
Author-email: manot <engineering@manot.ai>
License: MIT
Project-URL: Homepage, https://www.manot.ai
Project-URL: Documentation, https://api.manot.ai/api-documentation/v1
Project-URL: Source, https://github.com/manotai/manot-client
Classifier: Programming Language :: Python
Classifier: Programming Language :: Python :: 3
Classifier: Programming Language :: Python :: 3 :: Only
Classifier: Programming Language :: Python :: 3.8
Classifier: Programming Language :: Python :: 3.9
Classifier: Programming Language :: Python :: 3.10
Classifier: Programming Language :: Python :: 3.11
Classifier: License :: OSI Approved :: MIT License
Classifier: Operating System :: OS Independent
Requires-Python: >=3.8
License-File: LICENSE
Requires-Dist: requests >=2.28.1
Requires-Dist: Pillow ~=9.2.0
Requires-Dist: ipyplot ~=1.1.1
Requires-Dist: tqdm ~=4.64.1
